{
  "routing_json": "/workspace/Megatron-LM/tools/moe_profiler/data/routing_2.json",
  "hidden_size": 2048,
  "num_experts": 128,
  "topk": 8,
  "bh": 2,
  "bp": 2,
  "warmup_iters": 1,
  "iters": 3,
  "counts_are_assignments": false,
  "layers": {
    "layer_0": {
      "total_ms_avg": 1424.4951985677085,
      "total_ms_max": 1434.9735514322917,
      "dispatch_ms_avg": 710.3863949974377,
      "dispatch_ms_max": 710.7605150143305,
      "combine_ms_avg": 550.9393263657888,
      "combine_ms_max": 685.2274640401205,
      "preprocess_ms_avg": 133.66922634840012,
      "preprocess_ms_max": 300.4947803417842,
      "total_ms_per_rank": [
        1425.7295328776042,
        1434.9735514322917,
        1428.1922607421875,
        1409.08544921875
      ],
      "preprocess_ms_per_rank": [
        21.618515690167744,
        300.4947803417842,
        0.3908563454945882,
        212.17275301615396
      ],
      "dispatch_ms_per_rank": [
        710.3442444006602,
        709.7091806729635,
        710.7605150143305,
        710.7316399017969
      ],
      "combine_ms_per_rank": [
        662.9075387318929,
        395.5984703699748,
        685.2274640401205,
        460.023832321167
      ],
      "dispatch_bytes_per_rank": [
        356952192,
        345412224,
        329938176,
        315513216
      ],
      "combine_bytes_per_rank": [
        356777984,
        345243648,
        329777152,
        315359232
      ],
      "tokens_out_per_rank": [
        10888,
        10536,
        10064,
        9624
      ],
      "assignments_per_rank": [
        87104,
        84288,
        80512,
        76992
      ]
    },
    "layer_1": {
      "total_ms_avg": 1260.6733601888022,
      "total_ms_max": 1264.7345377604167,
      "dispatch_ms_avg": 617.3868437608083,
      "dispatch_ms_max": 617.6316257317861,
      "combine_ms_avg": 540.9965195953846,
      "combine_ms_max": 612.4849620262781,
      "preprocess_ms_avg": 72.02620568871498,
      "preprocess_ms_max": 134.24885535240173,
      "total_ms_per_rank": [
        1257.2194010416667,
        1263.6924641927083,
        1257.0470377604167,
        1264.7345377604167
      ],
      "preprocess_ms_per_rank": [
        26.6684650182724,
        126.88288299242656,
        0.30461939175923664,
        134.24885535240173
      ],
      "dispatch_ms_per_rank": [
        617.6316257317861,
        616.8424393335978,
        617.5481320619583,
        617.525177915891
      ],
      "combine_ms_per_rank": [
        579.9264566898346,
        489.00764695803326,
        612.4849620262781,
        482.5670127073924
      ],
      "dispatch_bytes_per_rank": [
        356952192,
        345412224,
        329938176,
        315513216
      ],
      "combine_bytes_per_rank": [
        356777984,
        345243648,
        329777152,
        315359232
      ],
      "tokens_out_per_rank": [
        10888,
        10536,
        10064,
        9624
      ],
      "assignments_per_rank": [
        87104,
        84288,
        80512,
        76992
      ]
    },
    "layer_10": {
      "total_ms_avg": 1420.417205810547,
      "total_ms_max": 1440.9683837890625,
      "dispatch_ms_avg": 717.8485614260038,
      "dispatch_ms_max": 718.3699953556061,
      "combine_ms_avg": 552.705143938462,
      "combine_ms_max": 638.6923486789068,
      "preprocess_ms_avg": 123.06357615192732,
      "preprocess_ms_max": 237.39985525608063,
      "total_ms_per_rank": [
        1411.0948893229167,
        1440.9683837890625,
        1388.8105875651042,
        1440.7949625651042
      ],
      "preprocess_ms_per_rank": [
        25.735288699467976,
        228.78022305170694,
        0.33893760045369464,
        237.39985525608063
      ],
      "dispatch_ms_per_rank": [
        718.0854229529699,
        717.0256417195002,
        718.3699953556061,
        717.913185675939
      ],
      "combine_ms_per_rank": [
        636.8800457318624,
        466.15219032764435,
        638.6923486789068,
        469.09599101543427
      ],
      "dispatch_bytes_per_rank": [
        356952192,
        345412224,
        329938176,
        315513216
      ],
      "combine_bytes_per_rank": [
        356777984,
        345243648,
        329777152,
        315359232
      ],
      "tokens_out_per_rank": [
        10888,
        10536,
        10064,
        9624
      ],
      "assignments_per_rank": [
        87104,
        84288,
        80512,
        76992
      ]
    },
    "layer_11": {
      "total_ms_avg": 1043.3116251627603,
      "total_ms_max": 1047.2315266927083,
      "dispatch_ms_avg": 509.0229463477929,
      "dispatch_ms_max": 510.1531053384145,
      "combine_ms_avg": 482.7695938249429,
      "combine_ms_max": 503.9965732892354,
      "preprocess_ms_avg": 24.2127636273702,
      "preprocess_ms_max": 52.56138332684835,
      "total_ms_per_rank": [
        1045.654541015625,
        1042.959716796875,
        1037.4007161458333,
        1047.2315266927083
      ],
      "preprocess_ms_per_rank": [
        0.35881861050923664,
        17.592015981674194,
        26.338836590449016,
        52.56138332684835
      ],
      "dispatch_ms_per_rank": [
        510.1531053384145,
        509.5290627479553,
        508.02857263882953,
        508.3810446659724
      ],
      "combine_ms_per_rank": [
        503.9965732892354,
        488.997678677241,
        479.8033489783605,
        458.2807743549347
      ],
      "dispatch_bytes_per_rank": [
        356952192,
        345412224,
        329938176,
        315513216
      ],
      "combine_bytes_per_rank": [
        356777984,
        345243648,
        329777152,
        315359232
      ],
      "tokens_out_per_rank": [
        10888,
        10536,
        10064,
        9624
      ],
      "assignments_per_rank": [
        87104,
        84288,
        80512,
        76992
      ]
    },
    "layer_12": {
      "total_ms_avg": 1289.8971150716147,
      "total_ms_max": 1291.3509928385417,
      "dispatch_ms_avg": 629.4056400060654,
      "dispatch_ms_max": 630.4826253255209,
      "combine_ms_avg": 533.3411115407944,
      "combine_ms_max": 628.6775026321411,
      "preprocess_ms_avg": 99.40287588040033,
      "preprocess_ms_max": 214.70935706297556,
      "total_ms_per_rank": [
        1291.0247395833333,
        1290.1522623697917,
        1291.3509928385417,
        1287.0604654947917
      ],
      "preprocess_ms_per_rank": [
        0.357455054918925,
        50.41048936049143,
        132.13420204321542,
        214.70935706297556
      ],
      "dispatch_ms_per_rank": [
        630.4826253255209,
        629.594441374143,
        628.6821626822153,
        628.8633306423823
      ],
      "combine_ms_per_rank": [
        628.6775026321411,
        577.7463616132736,
        512.7756436268488,
        414.1649382909139
      ],
      "dispatch_bytes_per_rank": [
        356952192,
        345412224,
        329938176,
        315513216
      ],
      "combine_bytes_per_rank": [
        356777984,
        345243648,
        329777152,
        315359232
      ],
      "tokens_out_per_rank": [
        10888,
        10536,
        10064,
        9624
      ],
      "assignments_per_rank": [
        87104,
        84288,
        80512,
        76992
      ]
    },
    "layer_13": {
      "total_ms_avg": 1141.9658406575522,
      "total_ms_max": 1145.1146240234375,
      "dispatch_ms_avg": 559.4690321683884,
      "dispatch_ms_max": 560.6223970254263,
      "combine_ms_avg": 497.8009975850582,
      "combine_ms_max": 555.1697473526001,
      "preprocess_ms_avg": 59.868076453606285,
      "preprocess_ms_max": 133.451913356781,
      "total_ms_per_rank": [
        1145.1146240234375,
        1141.9962565104167,
        1142.2034098307292,
        1138.549072265625
      ],
      "preprocess_ms_per_rank": [
        0.4147607485453288,
        57.889022986094155,
        133.451913356781,
        47.71660872300466
      ],
      "dispatch_ms_per_rank": [
        560.6223970254263,
        559.7630543311437,
        558.7285746733347,
        558.7621026436487
      ],
      "combine_ms_per_rank": [
        555.1697473526001,
        498.0231453180313,
        432.50435098012287,
        505.5067466894786
      ],
      "dispatch_bytes_per_rank": [
        356952192,
        345412224,
        329938176,
        315513216
      ],
      "combine_bytes_per_rank": [
        356777984,
        345243648,
        329777152,
        315359232
      ],
      "tokens_out_per_rank": [
        10888,
        10536,
        10064,
        9624
      ],
      "assignments_per_rank": [
        87104,
        84288,
        80512,
        76992
      ]
    },
    "layer_14": {
      "total_ms_avg": 1244.7049357096355,
      "total_ms_max": 1245.0262858072917,
      "dispatch_ms_avg": 607.173344184955,
      "dispatch_ms_max": 607.487801750501,
      "combine_ms_avg": 587.8541341821353,
      "combine_ms_max": 607.4562930663427,
      "preprocess_ms_avg": 22.71509224176407,
      "preprocess_ms_max": 56.30837003389994,
      "total_ms_per_rank": [
        1244.3641357421875,
        1244.8297119140625,
        1245.0262858072917,
        1244.599609375
      ],
      "preprocess_ms_per_rank": [
        11.863038659095764,
        22.305887659390766,
        0.3830726146697998,
        56.30837003389994
      ],
      "dispatch_ms_per_rank": [
        606.955195983251,
        606.9553623199463,
        607.487801750501,
        607.2950166861216
      ],
      "combine_ms_per_rank": [
        593.9686526457468,
        587.2536739905676,
        607.4562930663427,
        562.737917025884
      ],
      "dispatch_bytes_per_rank": [
        356952192,
        345412224,
        329938176,
        315513216
      ],
      "combine_bytes_per_rank": [
        356777984,
        345243648,
        329777152,
        315359232
      ],
      "tokens_out_per_rank": [
        10888,
        10536,
        10064,
        9624
      ],
      "assignments_per_rank": [
        87104,
        84288,
        80512,
        76992
      ]
    },
    "layer_15": {
      "total_ms_avg": 1403.4827880859373,
      "total_ms_max": 1416.6193440755208,
      "dispatch_ms_avg": 693.4287948211035,
      "dispatch_ms_max": 694.1855129798254,
      "combine_ms_avg": 652.868209262689,
      "combine_ms_max": 689.8835980494817,
      "preprocess_ms_avg": 29.09343534708023,
      "preprocess_ms_max": 47.52718460559845,
      "total_ms_per_rank": [
        1391.9781087239583,
        1416.6193440755208,
        1400.1011962890625,
        1405.2325032552083
      ],
      "preprocess_ms_per_rank": [
        28.214839259783428,
        0.4494389295578003,
        40.18227859338125,
        47.52718460559845
      ],
      "dispatch_ms_per_rank": [
        692.8218249877294,
        694.1855129798254,
        693.6419459978739,
        693.065895318985
      ],
      "combine_ms_per_rank": [
        640.6560730139414,
        689.8835980494817,
        636.9548133214315,
        643.9783526659012
      ],
      "dispatch_bytes_per_rank": [
        356952192,
        345412224,
        329938176,
        315513216
      ],
      "combine_bytes_per_rank": [
        356777984,
        345243648,
        329777152,
        315359232
      ],
      "tokens_out_per_rank": [
        10888,
        10536,
        10064,
        9624
      ],
      "assignments_per_rank": [
        87104,
        84288,
        80512,
        76992
      ]
    },
    "layer_16": {
      "total_ms_avg": 1504.1157938639324,
      "total_ms_max": 1508.1533610026042,
      "dispatch_ms_avg": 729.5620100696882,
      "dispatch_ms_max": 729.996661623319,
      "combine_ms_avg": 696.2301820516586,
      "combine_ms_max": 755.2509289582571,
      "preprocess_ms_avg": 51.407260328531265,
      "preprocess_ms_max": 95.75068366527557,
      "total_ms_per_rank": [
        1508.1533610026042,
        1507.016357421875,
        1499.2336018880208,
        1502.0598551432292
      ],
      "preprocess_ms_per_rank": [
        54.61113830407461,
        0.3567749659220378,
        54.910444378852844,
        95.75068366527557
      ],
      "dispatch_ms_per_rank": [
        728.933500011762,
        729.996661623319,
        729.5402326583862,
        729.7776459852854
      ],
      "combine_ms_per_rank": [
        692.3790469566981,
        755.2509289582571,
        686.3688776095709,
        650.9218746821085
      ],
      "dispatch_bytes_per_rank": [
        356952192,
        345412224,
        329938176,
        315513216
      ],
      "combine_bytes_per_rank": [
        356777984,
        345243648,
        329777152,
        315359232
      ],
      "tokens_out_per_rank": [
        10888,
        10536,
        10064,
        9624
      ],
      "assignments_per_rank": [
        87104,
        84288,
        80512,
        76992
      ]
    },
    "layer_17": {
      "total_ms_avg": 1300.4329528808594,
      "total_ms_max": 1301.8589680989583,
      "dispatch_ms_avg": 638.9551174342632,
      "dispatch_ms_max": 639.5108397006989,
      "combine_ms_avg": 571.163528084755,
      "combine_ms_max": 635.8729829390844,
      "preprocess_ms_avg": 64.2075740893682,
      "preprocess_ms_max": 114.84068600336711,
      "total_ms_per_rank": [
        1301.8589680989583,
        1301.7838541666667,
        1299.9625244140625,
        1298.12646484375
      ],
      "preprocess_ms_per_rank": [
        53.766862630844116,
        0.3116767406463623,
        87.91107098261516,
        114.84068600336711
      ],
      "dispatch_ms_per_rank": [
        638.0672893921534,
        639.5108397006989,
        639.167648990949,
        639.0746916532516
      ],
      "combine_ms_per_rank": [
        587.9382294019064,
        635.8729829390844,
        543.5886083046595,
        517.2542916933695
      ],
      "dispatch_bytes_per_rank": [
        356952192,
        345412224,
        329938176,
        315513216
      ],
      "combine_bytes_per_rank": [
        356777984,
        345243648,
        329777152,
        315359232
      ],
      "tokens_out_per_rank": [
        10888,
        10536,
        10064,
        9624
      ],
      "assignments_per_rank": [
        87104,
        84288,
        80512,
        76992
      ]
    },
    "layer_18": {
      "total_ms_avg": 1223.3193766276042,
      "total_ms_max": 1224.2240804036458,
      "dispatch_ms_avg": 595.9967049956322,
      "dispatch_ms_max": 596.8767362833023,
      "combine_ms_avg": 553.0127288202444,
      "combine_ms_max": 593.8482653299967,
      "preprocess_ms_avg": 45.259561459223434,
      "preprocess_ms_max": 114.67781798044841,
      "total_ms_per_rank": [
        1223.0536295572917,
        1222.18017578125,
        1223.8196207682292,
        1224.2240804036458
      ],
      "preprocess_ms_per_rank": [
        54.681740601857506,
        0.7008263270060221,
        10.977860927581787,
        114.67781798044841
      ],
      "dispatch_ms_per_rank": [
        595.1368993520737,
        596.8767362833023,
        595.8098083337148,
        596.1633760134379
      ],
      "combine_ms_per_rank": [
        542.2306736707687,
        593.8482653299967,
        590.6495006084442,
        485.3224756717682
      ],
      "dispatch_bytes_per_rank": [
        356952192,
        345412224,
        329938176,
        315513216
      ],
      "combine_bytes_per_rank": [
        356777984,
        345243648,
        329777152,
        315359232
      ],
      "tokens_out_per_rank": [
        10888,
        10536,
        10064,
        9624
      ],
      "assignments_per_rank": [
        87104,
        84288,
        80512,
        76992
      ]
    },
    "layer_19": {
      "total_ms_avg": 1223.8060302734375,
      "total_ms_max": 1224.5152180989583,
      "dispatch_ms_avg": 599.4873389204344,
      "dispatch_ms_max": 600.6524659792582,
      "combine_ms_avg": 541.8085006674131,
      "combine_ms_max": 592.8890930016836,
      "preprocess_ms_avg": 57.0046590367953,
      "preprocess_ms_max": 131.65806802113852,
      "total_ms_per_rank": [
        1222.6597493489583,
        1224.5152180989583,
        1224.3326416015625,
        1223.7165120442708
      ],
      "preprocess_ms_per_rank": [
        0.39858003457387287,
        25.899838010470074,
        70.06215008099873,
        131.65806802113852
      ],
      "dispatch_ms_per_rank": [
        600.6524659792582,
        599.6257530053457,
        598.9004859924316,
        598.7706507047018
      ],
      "combine_ms_per_rank": [
        592.8890930016836,
        574.7543216943741,
        526.6259862979254,
        472.96460167566937
      ],
      "dispatch_bytes_per_rank": [
        356952192,
        345412224,
        329938176,
        315513216
      ],
      "combine_bytes_per_rank": [
        356777984,
        345243648,
        329777152,
        315359232
      ],
      "tokens_out_per_rank": [
        10888,
        10536,
        10064,
        9624
      ],
      "assignments_per_rank": [
        87104,
        84288,
        80512,
        76992
      ]
    },
    "layer_2": {
      "total_ms_avg": 1085.4084981282551,
      "total_ms_max": 1089.2499593098958,
      "dispatch_ms_avg": 534.7566785216331,
      "dispatch_ms_max": 535.5474593639374,
      "combine_ms_avg": 468.92898776133853,
      "combine_ms_max": 522.4395250876745,
      "preprocess_ms_avg": 55.4540813267231,
      "preprocess_ms_max": 123.87981128692627,
      "total_ms_per_rank": [
        1087.9613850911458,
        1081.6392415364583,
        1089.2499593098958,
        1082.7834065755208
      ],
      "preprocess_ms_per_rank": [
        0.4248710076014201,
        47.093464970588684,
        123.87981128692627,
        50.418178041776024
      ],
      "dispatch_ms_per_rank": [
        535.5474593639374,
        534.5751483837763,
        534.4173953533173,
        534.4867109855016
      ],
      "combine_ms_per_rank": [
        522.4395250876745,
        480.6260283390681,
        403.2487943172455,
        469.40160330136615
      ],
      "dispatch_bytes_per_rank": [
        356952192,
        345412224,
        329938176,
        315513216
      ],
      "combine_bytes_per_rank": [
        356777984,
        345243648,
        329777152,
        315359232
      ],
      "tokens_out_per_rank": [
        10888,
        10536,
        10064,
        9624
      ],
      "assignments_per_rank": [
        87104,
        84288,
        80512,
        76992
      ]
    },
    "layer_20": {
      "total_ms_avg": 1156.015614827474,
      "total_ms_max": 1157.0285237630208,
      "dispatch_ms_avg": 562.8011311590672,
      "dispatch_ms_max": 563.637093702952,
      "combine_ms_avg": 500.30835626522696,
      "combine_ms_max": 557.9734263817469,
      "preprocess_ms_avg": 61.45735443631808,
      "preprocess_ms_max": 134.72214269638062,
      "total_ms_per_rank": [
        1157.0285237630208,
        1156.4929606119792,
        1154.9388834635417,
        1155.6020914713542
      ],
      "preprocess_ms_per_rank": [
        0.3730587164560954,
        52.72178200880686,
        58.012434323628746,
        134.72214269638062
      ],
      "dispatch_ms_per_rank": [
        563.4404652516047,
        563.637093702952,
        562.0394333600998,
        562.087532321612
      ],
      "combine_ms_per_rank": [
        557.9734263817469,
        506.2836712996165,
        508.2362233400345,
        428.7401040395101
      ],
      "dispatch_bytes_per_rank": [
        356952192,
        345412224,
        329938176,
        315513216
      ],
      "combine_bytes_per_rank": [
        356777984,
        345243648,
        329777152,
        315359232
      ],
      "tokens_out_per_rank": [
        10888,
        10536,
        10064,
        9624
      ],
      "assignments_per_rank": [
        87104,
        84288,
        80512,
        76992
      ]
    },
    "layer_21": {
      "total_ms_avg": 1156.1958312988284,
      "total_ms_max": 1158.8658854166667,
      "dispatch_ms_avg": 565.7797999183337,
      "dispatch_ms_max": 566.7819479703903,
      "combine_ms_avg": 493.17383351922035,
      "combine_ms_max": 561.1109533309937,
      "preprocess_ms_avg": 69.01790265242259,
      "preprocess_ms_max": 139.59544428189596,
      "total_ms_per_rank": [
        1158.8658854166667,
        1153.351318359375,
        1154.5419108072917,
        1158.0242106119792
      ],
      "preprocess_ms_per_rank": [
        0.33285733064015705,
        139.59544428189596,
        83.3205029964447,
        52.822806000709534
      ],
      "dispatch_ms_per_rank": [
        566.7819479703903,
        566.0477269887924,
        565.1891910235087,
        565.1003336906433
      ],
      "combine_ms_per_rank": [
        561.1109533309937,
        421.593182682991,
        477.18159739176434,
        512.8096006711324
      ],
      "dispatch_bytes_per_rank": [
        356952192,
        345412224,
        329938176,
        315513216
      ],
      "combine_bytes_per_rank": [
        356777984,
        345243648,
        329777152,
        315359232
      ],
      "tokens_out_per_rank": [
        10888,
        10536,
        10064,
        9624
      ],
      "assignments_per_rank": [
        87104,
        84288,
        80512,
        76992
      ]
    },
    "layer_22": {
      "total_ms_avg": 1270.6988423665366,
      "total_ms_max": 1271.3506266276042,
      "dispatch_ms_avg": 620.3755619724592,
      "dispatch_ms_max": 621.6320096651713,
      "combine_ms_avg": 525.6526475052038,
      "combine_ms_max": 617.3202649354935,
      "preprocess_ms_avg": 94.82263526320457,
      "preprocess_ms_max": 178.66252732276917,
      "total_ms_per_rank": [
        1270.7881266276042,
        1270.7102457682292,
        1269.9463704427083,
        1271.3506266276042
      ],
      "preprocess_ms_per_rank": [
        0.3259340127309163,
        147.19223233064017,
        53.10984738667806,
        178.66252732276917
      ],
      "dispatch_ms_per_rank": [
        621.6320096651713,
        620.585899313291,
        619.929771622022,
        619.3545672893524
      ],
      "combine_ms_per_rank": [
        617.3202649354935,
        471.5394256909688,
        566.9573730627695,
        446.7935263315837
      ],
      "dispatch_bytes_per_rank": [
        356952192,
        345412224,
        329938176,
        315513216
      ],
      "combine_bytes_per_rank": [
        356777984,
        345243648,
        329777152,
        315359232
      ],
      "tokens_out_per_rank": [
        10888,
        10536,
        10064,
        9624
      ],
      "assignments_per_rank": [
        87104,
        84288,
        80512,
        76992
      ]
    },
    "layer_23": {
      "total_ms_avg": 1132.6790974934897,
      "total_ms_max": 1134.5059814453125,
      "dispatch_ms_avg": 554.5986951291561,
      "dispatch_ms_max": 555.4718559583029,
      "combine_ms_avg": 528.2130259970824,
      "combine_ms_max": 542.0697766542435,
      "preprocess_ms_avg": 20.84624383846919,
      "preprocess_ms_max": 49.78778103987376,
      "total_ms_per_rank": [
        1134.5059814453125,
        1133.2598063151042,
        1132.1160074869792,
        1130.8345947265625
      ],
      "preprocess_ms_per_rank": [
        49.78778103987376,
        0.38825297355651855,
        11.92197068532308,
        21.286970655123394
      ],
      "dispatch_ms_per_rank": [
        553.7005279858907,
        555.4718559583029,
        554.4379793008169,
        554.7844172716141
      ],
      "combine_ms_per_rank": [
        505.9659029642741,
        542.0697766542435,
        538.230102022489,
        526.5863223473231
      ],
      "dispatch_bytes_per_rank": [
        356952192,
        345412224,
        329938176,
        315513216
      ],
      "combine_bytes_per_rank": [
        356777984,
        345243648,
        329777152,
        315359232
      ],
      "tokens_out_per_rank": [
        10888,
        10536,
        10064,
        9624
      ],
      "assignments_per_rank": [
        87104,
        84288,
        80512,
        76992
      ]
    },
    "layer_24": {
      "total_ms_avg": 1280.1507873535156,
      "total_ms_max": 1281.3253987630208,
      "dispatch_ms_avg": 623.639566252629,
      "dispatch_ms_max": 624.8932029803594,
      "combine_ms_avg": 553.1622730294863,
      "combine_ms_max": 624.1581353346506,
      "preprocess_ms_avg": 73.38240741690001,
      "preprocess_ms_max": 158.87195801734924,
      "total_ms_per_rank": [
        1280.5355631510417,
        1281.3253987630208,
        1279.1429036458333,
        1279.5992838541667
      ],
      "preprocess_ms_per_rank": [
        0.3141163190205892,
        53.93640196323395,
        80.40715336799622,
        158.87195801734924
      ],
      "dispatch_ms_per_rank": [
        624.8932029803594,
        623.7341443697611,
        622.979576309522,
        622.9513413508733
      ],
      "combine_ms_per_rank": [
        624.1581353346506,
        570.4668710629145,
        549.40214240551,
        468.6219433148702
      ],
      "dispatch_bytes_per_rank": [
        356952192,
        345412224,
        329938176,
        315513216
      ],
      "combine_bytes_per_rank": [
        356777984,
        345243648,
        329777152,
        315359232
      ],
      "tokens_out_per_rank": [
        10888,
        10536,
        10064,
        9624
      ],
      "assignments_per_rank": [
        87104,
        84288,
        80512,
        76992
      ]
    },
    "layer_25": {
      "total_ms_avg": 1377.8833007812498,
      "total_ms_max": 1378.783935546875,
      "dispatch_ms_avg": 674.1228731870651,
      "dispatch_ms_max": 675.0545210440954,
      "combine_ms_avg": 525.9739863673846,
      "combine_ms_max": 671.2954796950022,
      "preprocess_ms_avg": 150.85666828354198,
      "preprocess_ms_max": 282.3967756827672,
      "total_ms_per_rank": [
        1376.6348470052083,
        1378.783935546875,
        1377.7871907552083,
        1378.3272298177083
      ],
      "preprocess_ms_per_rank": [
        0.33038703600565594,
        266.5052350362142,
        282.3967756827672,
        54.19427537918091
      ],
      "dispatch_ms_per_rank": [
        675.0545210440954,
        674.4504283269247,
        673.2948733568192,
        673.6916700204214
      ],
      "combine_ms_per_rank": [
        671.2954796950022,
        406.2665600379308,
        404.4288296699524,
        621.9050760666529
      ],
      "dispatch_bytes_per_rank": [
        356952192,
        345412224,
        329938176,
        315513216
      ],
      "combine_bytes_per_rank": [
        356777984,
        345243648,
        329777152,
        315359232
      ],
      "tokens_out_per_rank": [
        10888,
        10536,
        10064,
        9624
      ],
      "assignments_per_rank": [
        87104,
        84288,
        80512,
        76992
      ]
    },
    "layer_26": {
      "total_ms_avg": 1206.1881205240886,
      "total_ms_max": 1208.9313557942708,
      "dispatch_ms_avg": 589.9812372326851,
      "dispatch_ms_max": 590.4139646689097,
      "combine_ms_avg": 563.3117404282093,
      "combine_ms_max": 587.2307436863581,
      "preprocess_ms_avg": 24.598821332057316,
      "preprocess_ms_max": 44.85344696044922,
      "total_ms_per_rank": [
        1205.4527994791667,
        1208.9313557942708,
        1208.82958984375,
        1201.5387369791667
      ],
      "preprocess_ms_per_rank": [
        44.85344696044922,
        12.103455344835917,
        0.3398306369781494,
        41.09855238596598
      ],
      "dispatch_ms_per_rank": [
        589.6917876005173,
        589.579362988472,
        590.4139646689097,
        590.2398336728414
      ],
      "combine_ms_per_rank": [
        540.7267045974731,
        576.1300510168076,
        587.2307436863581,
        549.1594624121984
      ],
      "dispatch_bytes_per_rank": [
        356952192,
        345412224,
        329938176,
        315513216
      ],
      "combine_bytes_per_rank": [
        356777984,
        345243648,
        329777152,
        315359232
      ],
      "tokens_out_per_rank": [
        10888,
        10536,
        10064,
        9624
      ],
      "assignments_per_rank": [
        87104,
        84288,
        80512,
        76992
      ]
    },
    "layer_27": {
      "total_ms_avg": 1311.0884704589844,
      "total_ms_max": 1311.7047526041667,
      "dispatch_ms_avg": 640.3566889762878,
      "dispatch_ms_max": 641.2128226359686,
      "combine_ms_avg": 613.0724203586577,
      "combine_ms_max": 636.8798636595408,
      "preprocess_ms_avg": 29.051857322454453,
      "preprocess_ms_max": 53.301801323890686,
      "total_ms_per_rank": [
        1310.691650390625,
        1311.7047526041667,
        1311.2439778645833,
        1310.7135009765625
      ],
      "preprocess_ms_per_rank": [
        53.301801323890686,
        0.3768693208694458,
        36.10686266422272,
        26.42189598083496
      ],
      "dispatch_ms_per_rank": [
        639.670447309812,
        641.2128226359686,
        640.4432266553243,
        640.1002593040466
      ],
      "combine_ms_per_rank": [
        586.0261679887772,
        636.8798636595408,
        604.9835007588068,
        624.4001490275065
      ],
      "dispatch_bytes_per_rank": [
        356952192,
        345412224,
        329938176,
        315513216
      ],
      "combine_bytes_per_rank": [
        356777984,
        345243648,
        329777152,
        315359232
      ],
      "tokens_out_per_rank": [
        10888,
        10536,
        10064,
        9624
      ],
      "assignments_per_rank": [
        87104,
        84288,
        80512,
        76992
      ]
    },
    "layer_28": {
      "total_ms_avg": 1543.4717712402344,
      "total_ms_max": 1544.2128092447917,
      "dispatch_ms_avg": 746.7060464223226,
      "dispatch_ms_max": 747.0688577095667,
      "combine_ms_avg": 703.724490950505,
      "combine_ms_max": 770.2417337497076,
      "preprocess_ms_avg": 64.03265842795372,
      "preprocess_ms_max": 117.276673634847,
      "total_ms_per_rank": [
        1544.0080159505208,
        1542.7338053385417,
        1542.9324544270833,
        1544.2128092447917
      ],
      "preprocess_ms_per_rank": [
        54.22465674082438,
        0.4216943184534709,
        84.20760901769002,
        117.276673634847
      ],
      "dispatch_ms_per_rank": [
        746.1227006912231,
        747.0688577095667,
        746.8260572751363,
        746.8065700133642
      ],
      "combine_ms_per_rank": [
        711.5057977437973,
        770.2417337497076,
        680.3458356459936,
        652.8045966625214
      ],
      "dispatch_bytes_per_rank": [
        356952192,
        345412224,
        329938176,
        315513216
      ],
      "combine_bytes_per_rank": [
        356777984,
        345243648,
        329777152,
        315359232
      ],
      "tokens_out_per_rank": [
        10888,
        10536,
        10064,
        9624
      ],
      "assignments_per_rank": [
        87104,
        84288,
        80512,
        76992
      ]
    },
    "layer_29": {
      "total_ms_avg": 1230.1783955891929,
      "total_ms_max": 1230.8858642578125,
      "dispatch_ms_avg": 603.9863509138426,
      "dispatch_ms_max": 604.5553323825201,
      "combine_ms_avg": 545.6497928500175,
      "combine_ms_max": 594.2331090370814,
      "preprocess_ms_avg": 52.808493852615356,
      "preprocess_ms_max": 86.68247270584106,
      "total_ms_per_rank": [
        1229.3802897135417,
        1229.7905680338542,
        1230.6568603515625,
        1230.8858642578125
      ],
      "preprocess_ms_per_rank": [
        53.20076366265615,
        0.33819393316904706,
        71.01254510879517,
        86.68247270584106
      ],
      "dispatch_ms_per_rank": [
        603.0864406029383,
        604.5553323825201,
        604.2977916797003,
        604.0058389902115
      ],
      "combine_ms_per_rank": [
        550.0411503314972,
        594.2331090370814,
        527.5192716916403,
        510.8056403398514
      ],
      "dispatch_bytes_per_rank": [
        356952192,
        345412224,
        329938176,
        315513216
      ],
      "combine_bytes_per_rank": [
        356777984,
        345243648,
        329777152,
        315359232
      ],
      "tokens_out_per_rank": [
        10888,
        10536,
        10064,
        9624
      ],
      "assignments_per_rank": [
        87104,
        84288,
        80512,
        76992
      ]
    },
    "layer_3": {
      "total_ms_avg": 1150.585428873698,
      "total_ms_max": 1151.5371500651042,
      "dispatch_ms_avg": 561.3526673416296,
      "dispatch_ms_max": 562.6512383619944,
      "combine_ms_avg": 533.0171799063683,
      "combine_ms_max": 558.5015236536661,
      "preprocess_ms_avg": 30.00031500061353,
      "preprocess_ms_max": 57.44245433807373,
      "total_ms_per_rank": [
        1151.5245361328125,
        1148.3299560546875,
        1150.9500732421875,
        1151.5371500651042
      ],
      "preprocess_ms_per_rank": [
        0.35528135299682617,
        17.085363666216534,
        45.11816064516703,
        57.44245433807373
      ],
      "dispatch_ms_per_rank": [
        562.6512383619944,
        561.5315450032552,
        560.9438963333765,
        560.2839896678925
      ],
      "combine_ms_per_rank": [
        558.5015236536661,
        539.9387509822845,
        516.2305863698324,
        517.3978586196899
      ],
      "dispatch_bytes_per_rank": [
        356952192,
        345412224,
        329938176,
        315513216
      ],
      "combine_bytes_per_rank": [
        356777984,
        345243648,
        329777152,
        315359232
      ],
      "tokens_out_per_rank": [
        10888,
        10536,
        10064,
        9624
      ],
      "assignments_per_rank": [
        87104,
        84288,
        80512,
        76992
      ]
    },
    "layer_30": {
      "total_ms_avg": 1216.0346577962239,
      "total_ms_max": 1217.5531005859375,
      "dispatch_ms_avg": 598.0340502560139,
      "dispatch_ms_max": 598.8426959911982,
      "combine_ms_avg": 550.3402639230093,
      "combine_ms_max": 586.5552067359289,
      "preprocess_ms_avg": 41.175529181957245,
      "preprocess_ms_max": 92.42917672793071,
      "total_ms_per_rank": [
        1216.6458333333333,
        1217.5531005859375,
        1213.6727701822917,
        1216.2669270833333
      ],
      "preprocess_ms_per_rank": [
        41.89405163129171,
        0.4000036319096883,
        29.97888473669688,
        92.42917672793071
      ],
      "dispatch_ms_per_rank": [
        597.1024860541025,
        598.8426959911982,
        597.9027863343557,
        598.288232644399
      ],
      "combine_ms_per_rank": [
        554.9650906324387,
        586.5552067359289,
        557.2873142957687,
        502.5534440279007
      ],
      "dispatch_bytes_per_rank": [
        356952192,
        345412224,
        329938176,
        315513216
      ],
      "combine_bytes_per_rank": [
        356777984,
        345243648,
        329777152,
        315359232
      ],
      "tokens_out_per_rank": [
        10888,
        10536,
        10064,
        9624
      ],
      "assignments_per_rank": [
        87104,
        84288,
        80512,
        76992
      ]
    },
    "layer_31": {
      "total_ms_avg": 1202.0510660807292,
      "total_ms_max": 1203.7532958984375,
      "dispatch_ms_avg": 584.2251293460528,
      "dispatch_ms_max": 585.3485940297445,
      "combine_ms_avg": 538.6333185633023,
      "combine_ms_max": 584.1660243670145,
      "preprocess_ms_avg": 49.835594822963074,
      "preprocess_ms_max": 109.01265164216359,
      "total_ms_per_rank": [
        1203.0364583333333,
        1203.7532958984375,
        1200.0652262369792,
        1201.3492838541667
      ],
      "preprocess_ms_per_rank": [
        0.33147064844767254,
        15.711462696393331,
        74.28679430484772,
        109.01265164216359
      ],
      "dispatch_ms_per_rank": [
        585.3485940297445,
        584.3940037091573,
        583.6477692921957,
        583.5101503531138
      ],
      "combine_ms_per_rank": [
        584.1660243670145,
        568.7814422448477,
        516.9963989655176,
        484.5894086758296
      ],
      "dispatch_bytes_per_rank": [
        356952192,
        345412224,
        329938176,
        315513216
      ],
      "combine_bytes_per_rank": [
        356777984,
        345243648,
        329777152,
        315359232
      ],
      "tokens_out_per_rank": [
        10888,
        10536,
        10064,
        9624
      ],
      "assignments_per_rank": [
        87104,
        84288,
        80512,
        76992
      ]
    },
    "layer_32": {
      "total_ms_avg": 1169.4061075846353,
      "total_ms_max": 1171.2091878255208,
      "dispatch_ms_avg": 568.9202634990215,
      "dispatch_ms_max": 569.6002119382223,
      "combine_ms_avg": 488.96893933415413,
      "combine_ms_max": 571.4598629872004,
      "preprocess_ms_avg": 81.73614111542702,
      "preprocess_ms_max": 167.81339967250824,
      "total_ms_per_rank": [
        1171.2091878255208,
        1170.0589192708333,
        1168.451904296875,
        1167.9044189453125
      ],
      "preprocess_ms_per_rank": [
        0.325830340385437,
        50.5982164144516,
        108.2071180343628,
        167.81339967250824
      ],
      "dispatch_ms_per_rank": [
        569.6002119382223,
        568.9201837380728,
        568.6776396830877,
        568.4830186367035
      ],
      "combine_ms_per_rank": [
        571.4598629872004,
        516.8344336350759,
        463.67589970429736,
        403.90556101004285
      ],
      "dispatch_bytes_per_rank": [
        356952192,
        345412224,
        329938176,
        315513216
      ],
      "combine_bytes_per_rank": [
        356777984,
        345243648,
        329777152,
        315359232
      ],
      "tokens_out_per_rank": [
        10888,
        10536,
        10064,
        9624
      ],
      "assignments_per_rank": [
        87104,
        84288,
        80512,
        76992
      ]
    },
    "layer_33": {
      "total_ms_avg": 1193.3911946614583,
      "total_ms_max": 1195.55859375,
      "dispatch_ms_avg": 581.4828622539839,
      "dispatch_ms_max": 582.4245949586233,
      "combine_ms_avg": 498.63050194581353,
      "combine_ms_max": 577.1717546780905,
      "preprocess_ms_avg": 82.50577499469121,
      "preprocess_ms_max": 178.762357989947,
      "total_ms_per_rank": [
        1195.55859375,
        1193.7310791015625,
        1189.7545166015625,
        1194.5205891927083
      ],
      "preprocess_ms_per_rank": [
        0.3335040012995402,
        178.762357989947,
        97.52438628673553,
        53.402851700782776
      ],
      "dispatch_ms_per_rank": [
        582.4245949586233,
        581.8168429931005,
        580.9166319767634,
        580.7733790874481
      ],
      "combine_ms_per_rank": [
        577.1717546780905,
        405.4187406698863,
        484.6481850544612,
        527.2833273808161
      ],
      "dispatch_bytes_per_rank": [
        356952192,
        345412224,
        329938176,
        315513216
      ],
      "combine_bytes_per_rank": [
        356777984,
        345243648,
        329777152,
        315359232
      ],
      "tokens_out_per_rank": [
        10888,
        10536,
        10064,
        9624
      ],
      "assignments_per_rank": [
        87104,
        84288,
        80512,
        76992
      ]
    },
    "layer_34": {
      "total_ms_avg": 1385.3027038574219,
      "total_ms_max": 1386.6280924479167,
      "dispatch_ms_avg": 678.2272232472897,
      "dispatch_ms_max": 679.3806349833807,
      "combine_ms_avg": 541.9519623120626,
      "combine_ms_max": 675.8746809959412,
      "preprocess_ms_avg": 137.4973405798276,
      "preprocess_ms_max": 261.9694663286209,
      "total_ms_per_rank": [
        1386.6280924479167,
        1385.6761067708333,
        1383.0939127604167,
        1385.8127034505208
      ],
      "preprocess_ms_per_rank": [
        0.4552324215571086,
        236.94845962524414,
        50.616203943888344,
        261.9694663286209
      ],
      "dispatch_ms_per_rank": [
        679.3806349833807,
        678.3104037046432,
        677.9077796141306,
        677.3100746870041
      ],
      "combine_ms_per_rank": [
        675.8746809959412,
        441.05365097522736,
        624.6830333073934,
        426.1964839696884
      ],
      "dispatch_bytes_per_rank": [
        356952192,
        345412224,
        329938176,
        315513216
      ],
      "combine_bytes_per_rank": [
        356777984,
        345243648,
        329777152,
        315359232
      ],
      "tokens_out_per_rank": [
        10888,
        10536,
        10064,
        9624
      ],
      "assignments_per_rank": [
        87104,
        84288,
        80512,
        76992
      ]
    },
    "layer_35": {
      "total_ms_avg": 1156.4081420898438,
      "total_ms_max": 1157.2329508463542,
      "dispatch_ms_avg": 566.2823379337788,
      "dispatch_ms_max": 567.1351230144501,
      "combine_ms_avg": 541.4240656892458,
      "combine_ms_max": 556.1489890019099,
      "preprocess_ms_avg": 21.38579893112183,
      "preprocess_ms_max": 52.472164948781334,
      "total_ms_per_rank": [
        1156.3861490885417,
        1157.2329508463542,
        1155.3580322265625,
        1156.6554361979167
      ],
      "preprocess_ms_per_rank": [
        52.472164948781334,
        0.42425139745076496,
        12.174293677012125,
        20.472485701243084
      ],
      "dispatch_ms_per_rank": [
        565.514954328537,
        567.1351230144501,
        566.1834797064463,
        566.2957946856817
      ],
      "combine_ms_per_rank": [
        512.916132013003,
        554.6603940327963,
        556.1489890019099,
        541.9707477092743
      ],
      "dispatch_bytes_per_rank": [
        356952192,
        345412224,
        329938176,
        315513216
      ],
      "combine_bytes_per_rank": [
        356777984,
        345243648,
        329777152,
        315359232
      ],
      "tokens_out_per_rank": [
        10888,
        10536,
        10064,
        9624
      ],
      "assignments_per_rank": [
        87104,
        84288,
        80512,
        76992
      ]
    },
    "layer_36": {
      "total_ms_avg": 1088.9200744628909,
      "total_ms_max": 1090.4377848307292,
      "dispatch_ms_avg": 531.2343187630177,
      "dispatch_ms_max": 531.7557836373647,
      "combine_ms_avg": 500.2060492535432,
      "combine_ms_max": 523.6073446671168,
      "preprocess_ms_avg": 27.178947418928146,
      "preprocess_ms_max": 69.65495729446411,
      "total_ms_per_rank": [
        1090.4377848307292,
        1088.08056640625,
        1088.1573893229167,
        1089.0045572916667
      ],
      "preprocess_ms_per_rank": [
        11.35714570681254,
        27.313993016878765,
        0.3896936575571696,
        69.65495729446411
      ],
      "dispatch_ms_per_rank": [
        530.680221358935,
        530.8053513765335,
        531.7557836373647,
        531.6959186792374
      ],
      "combine_ms_per_rank": [
        521.1855206886927,
        497.62361594041187,
        523.6073446671168,
        458.4077157179515
      ],
      "dispatch_bytes_per_rank": [
        356952192,
        345412224,
        329938176,
        315513216
      ],
      "combine_bytes_per_rank": [
        356777984,
        345243648,
        329777152,
        315359232
      ],
      "tokens_out_per_rank": [
        10888,
        10536,
        10064,
        9624
      ],
      "assignments_per_rank": [
        87104,
        84288,
        80512,
        76992
      ]
    },
    "layer_37": {
      "total_ms_avg": 1438.182403564453,
      "total_ms_max": 1442.4746907552083,
      "dispatch_ms_avg": 703.7788839836915,
      "dispatch_ms_max": 704.6169823408127,
      "combine_ms_avg": 528.5647697846094,
      "combine_ms_max": 700.4409699440002,
      "preprocess_ms_avg": 177.54369341333708,
      "preprocess_ms_max": 334.65834629535675,
      "total_ms_per_rank": [
        1436.8000081380208,
        1438.677001953125,
        1442.4746907552083,
        1434.7779134114583
      ],
      "preprocess_ms_per_rank": [
        0.3435923258463542,
        334.65834629535675,
        324.3966280221939,
        50.77620700995127
      ],
      "dispatch_ms_per_rank": [
        704.6169823408127,
        704.20441198349,
        702.8655929962794,
        703.428548614184
      ],
      "combine_ms_per_rank": [
        700.4409699440002,
        370.49775501092273,
        391.6860279242198,
        651.6343262592951
      ],
      "dispatch_bytes_per_rank": [
        356952192,
        345412224,
        329938176,
        315513216
      ],
      "combine_bytes_per_rank": [
        356777984,
        345243648,
        329777152,
        315359232
      ],
      "tokens_out_per_rank": [
        10888,
        10536,
        10064,
        9624
      ],
      "assignments_per_rank": [
        87104,
        84288,
        80512,
        76992
      ]
    },
    "layer_38": {
      "total_ms_avg": 1243.4730529785156,
      "total_ms_max": 1244.737548828125,
      "dispatch_ms_avg": 605.2428820729256,
      "dispatch_ms_max": 605.8598813215891,
      "combine_ms_avg": 583.6942360500494,
      "combine_ms_max": 604.2857229709625,
      "preprocess_ms_avg": 27.94806283712387,
      "preprocess_ms_max": 66.68242800235748,
      "total_ms_per_rank": [
        1242.5519612630208,
        1244.0323079427083,
        1242.5703938802083,
        1244.737548828125
      ],
      "preprocess_ms_per_rank": [
        3.427992304166158,
        34.40933867295583,
        7.272492369016011,
        66.68242800235748
      ],
      "dispatch_ms_per_rank": [
        605.8598813215891,
        605.4470006227493,
        605.0392900307974,
        604.6253563165665
      ],
      "combine_ms_per_rank": [
        604.2857229709625,
        574.4669849475225,
        600.1526976029078,
        555.871538678805
      ],
      "dispatch_bytes_per_rank": [
        356952192,
        345412224,
        329938176,
        315513216
      ],
      "combine_bytes_per_rank": [
        356777984,
        345243648,
        329777152,
        315359232
      ],
      "tokens_out_per_rank": [
        10888,
        10536,
        10064,
        9624
      ],
      "assignments_per_rank": [
        87104,
        84288,
        80512,
        76992
      ]
    },
    "layer_39": {
      "total_ms_avg": 1348.1863708496094,
      "total_ms_max": 1353.9805501302083,
      "dispatch_ms_avg": 662.7542871634166,
      "dispatch_ms_max": 663.6980719566345,
      "combine_ms_avg": 631.8547121584415,
      "combine_ms_max": 657.9855582714081,
      "preprocess_ms_avg": 27.18223744630814,
      "preprocess_ms_max": 52.44212671120962,
      "total_ms_per_rank": [
        1352.4940999348958,
        1353.9805501302083,
        1342.0175374348958,
        1344.2532958984375
      ],
      "preprocess_ms_per_rank": [
        52.44212671120962,
        0.35708268483479816,
        29.011471668879192,
        26.91826872030894
      ],
      "dispatch_ms_per_rank": [
        662.0515966415405,
        663.6980719566345,
        662.7340650161108,
        662.5334150393804
      ],
      "combine_ms_per_rank": [
        608.826107343038,
        657.9855582714081,
        622.0741403500239,
        638.5330426692963
      ],
      "dispatch_bytes_per_rank": [
        356952192,
        345412224,
        329938176,
        315513216
      ],
      "combine_bytes_per_rank": [
        356777984,
        345243648,
        329777152,
        315359232
      ],
      "tokens_out_per_rank": [
        10888,
        10536,
        10064,
        9624
      ],
      "assignments_per_rank": [
        87104,
        84288,
        80512,
        76992
      ]
    },
    "layer_4": {
      "total_ms_avg": 1099.307362874349,
      "total_ms_max": 1100.6536051432292,
      "dispatch_ms_avg": 539.7890250682831,
      "dispatch_ms_max": 540.7728716929754,
      "combine_ms_avg": 461.3498737514019,
      "combine_ms_max": 525.625284632047,
      "preprocess_ms_avg": 69.84308472275734,
      "preprocess_ms_max": 128.36178533236185,
      "total_ms_per_rank": [
        1100.6536051432292,
        1098.285400390625,
        1099.9132080078125,
        1098.3772379557292
      ],
      "preprocess_ms_per_rank": [
        0.33279597759246826,
        49.74401966730753,
        128.36178533236185,
        100.9337379137675
      ],
      "dispatch_ms_per_rank": [
        540.7728716929754,
        539.676312327385,
        539.3766736189524,
        539.3302426338196
      ],
      "combine_ms_per_rank": [
        525.625284632047,
        486.74297201633453,
        401.2840446631114,
        431.7471936941147
      ],
      "dispatch_bytes_per_rank": [
        356952192,
        345412224,
        329938176,
        315513216
      ],
      "combine_bytes_per_rank": [
        356777984,
        345243648,
        329777152,
        315359232
      ],
      "tokens_out_per_rank": [
        10888,
        10536,
        10064,
        9624
      ],
      "assignments_per_rank": [
        87104,
        84288,
        80512,
        76992
      ]
    },
    "layer_40": {
      "total_ms_avg": 1371.4510498046875,
      "total_ms_max": 1372.7501627604167,
      "dispatch_ms_avg": 670.1348085900147,
      "dispatch_ms_max": 670.6227259635925,
      "combine_ms_avg": 623.8755982518197,
      "combine_ms_max": 674.2818343639374,
      "preprocess_ms_avg": 48.334606667359665,
      "preprocess_ms_max": 115.43992733955383,
      "total_ms_per_rank": [
        1372.7501627604167,
        1372.2555745442708,
        1369.8945719401042,
        1370.9038899739583
      ],
      "preprocess_ms_per_rank": [
        53.411996046702065,
        0.37441666920979816,
        24.11208661397298,
        115.43992733955383
      ],
      "dispatch_ms_per_rank": [
        669.4075841108958,
        670.6227259635925,
        670.0760856072108,
        670.43283867836
      ],
      "combine_ms_per_rank": [
        619.0212549765905,
        674.2818343639374,
        645.6904689868292,
        556.5088346799215
      ],
      "dispatch_bytes_per_rank": [
        356952192,
        345412224,
        329938176,
        315513216
      ],
      "combine_bytes_per_rank": [
        356777984,
        345243648,
        329777152,
        315359232
      ],
      "tokens_out_per_rank": [
        10888,
        10536,
        10064,
        9624
      ],
      "assignments_per_rank": [
        87104,
        84288,
        80512,
        76992
      ]
    },
    "layer_41": {
      "total_ms_avg": 1212.9944763183594,
      "total_ms_max": 1213.7537027994792,
      "dispatch_ms_avg": 595.9795618355274,
      "dispatch_ms_max": 596.7454209327698,
      "combine_ms_avg": 537.356683075428,
      "combine_ms_max": 584.1977090438207,
      "preprocess_ms_avg": 50.11212549606959,
      "preprocess_ms_max": 86.90383394559224,
      "total_ms_per_rank": [
        1211.7347005208333,
        1213.7537027994792,
        1213.6697184244792,
        1212.8197835286458
      ],
      "preprocess_ms_per_rank": [
        51.216041366259255,
        0.3695433537165324,
        61.95908331871033,
        86.90383394559224
      ],
      "dispatch_ms_per_rank": [
        595.1088710228602,
        596.7454209327698,
        596.1963673830032,
        595.8675880034765
      ],
      "combine_ms_per_rank": [
        542.8506716092428,
        584.1977090438207,
        526.1760476827621,
        496.2023039658864
      ],
      "dispatch_bytes_per_rank": [
        356952192,
        345412224,
        329938176,
        315513216
      ],
      "combine_bytes_per_rank": [
        356777984,
        345243648,
        329777152,
        315359232
      ],
      "tokens_out_per_rank": [
        10888,
        10536,
        10064,
        9624
      ],
      "assignments_per_rank": [
        87104,
        84288,
        80512,
        76992
      ]
    },
    "layer_42": {
      "total_ms_avg": 1716.3462727864585,
      "total_ms_max": 1719.1201985677083,
      "dispatch_ms_avg": 842.0405895014604,
      "dispatch_ms_max": 842.4518403609594,
      "combine_ms_avg": 772.9283024867376,
      "combine_ms_max": 836.364030679067,
      "preprocess_ms_avg": 68.69994659225145,
      "preprocess_ms_max": 118.49100470542908,
      "total_ms_per_rank": [
        1713.4161783854167,
        1715.0071207682292,
        1719.1201985677083,
        1717.8415934244792
      ],
      "preprocess_ms_per_rank": [
        52.57628929615021,
        0.4344879786173503,
        103.2980043888092,
        118.49100470542908
      ],
      "dispatch_ms_per_rank": [
        841.7161339521408,
        842.4518403609594,
        842.0436090230942,
        841.9507746696472
      ],
      "combine_ms_per_rank": [
        788.0836839278539,
        836.364030679067,
        741.1936330000559,
        726.0718623399734
      ],
      "dispatch_bytes_per_rank": [
        356952192,
        345412224,
        329938176,
        315513216
      ],
      "combine_bytes_per_rank": [
        356777984,
        345243648,
        329777152,
        315359232
      ],
      "tokens_out_per_rank": [
        10888,
        10536,
        10064,
        9624
      ],
      "assignments_per_rank": [
        87104,
        84288,
        80512,
        76992
      ]
    },
    "layer_43": {
      "total_ms_avg": 1072.6981913248699,
      "total_ms_max": 1075.7918701171875,
      "dispatch_ms_avg": 527.4534576336544,
      "dispatch_ms_max": 528.488064289093,
      "combine_ms_avg": 462.03066457311314,
      "combine_ms_max": 512.7993923823038,
      "preprocess_ms_avg": 55.946972995996475,
      "preprocess_ms_max": 97.58477234840393,
      "total_ms_per_rank": [
        1072.6942545572917,
        1070.9309488932292,
        1075.7918701171875,
        1071.3756917317708
      ],
      "preprocess_ms_per_rank": [
        0.33581626415252686,
        50.8217853307724,
        75.04551804065704,
        97.58477234840393
      ],
      "dispatch_ms_per_rank": [
        528.488064289093,
        527.2281006177267,
        527.2142643531164,
        526.8834012746811
      ],
      "combine_ms_per_rank": [
        512.7993923823038,
        473.6619939804077,
        445.2079616387685,
        416.4533102909724
      ],
      "dispatch_bytes_per_rank": [
        356952192,
        345412224,
        329938176,
        315513216
      ],
      "combine_bytes_per_rank": [
        356777984,
        345243648,
        329777152,
        315359232
      ],
      "tokens_out_per_rank": [
        10888,
        10536,
        10064,
        9624
      ],
      "assignments_per_rank": [
        87104,
        84288,
        80512,
        76992
      ]
    },
    "layer_44": {
      "total_ms_avg": 1320.2170104980469,
      "total_ms_max": 1329.2735188802083,
      "dispatch_ms_avg": 650.5376231571039,
      "dispatch_ms_max": 651.3783855835596,
      "combine_ms_avg": 610.8101242184639,
      "combine_ms_max": 648.3410829305649,
      "preprocess_ms_avg": 31.68390383323033,
      "preprocess_ms_max": 54.06236366430918,
      "total_ms_per_rank": [
        1313.8995361328125,
        1329.2735188802083,
        1312.897705078125,
        1324.7972819010417
      ],
      "preprocess_ms_per_rank": [
        38.77676165103912,
        0.3791503111521403,
        33.5173397064209,
        54.06236366430918
      ],
      "dispatch_ms_per_rank": [
        649.7574780384699,
        651.3783855835596,
        650.849259297053,
        650.1653697093328
      ],
      "combine_ms_per_rank": [
        596.3556122382482,
        648.3410829305649,
        600.2702299753824,
        598.27357172966
      ],
      "dispatch_bytes_per_rank": [
        356952192,
        345412224,
        329938176,
        315513216
      ],
      "combine_bytes_per_rank": [
        356777984,
        345243648,
        329777152,
        315359232
      ],
      "tokens_out_per_rank": [
        10888,
        10536,
        10064,
        9624
      ],
      "assignments_per_rank": [
        87104,
        84288,
        80512,
        76992
      ]
    },
    "layer_45": {
      "total_ms_avg": 1552.5403238932292,
      "total_ms_max": 1553.5721842447917,
      "dispatch_ms_avg": 761.2483410040537,
      "dispatch_ms_max": 761.8198849360148,
      "combine_ms_avg": 727.4845428864162,
      "combine_ms_max": 758.0486620267233,
      "preprocess_ms_avg": 33.9841745297114,
      "preprocess_ms_max": 56.912907679875694,
      "total_ms_per_rank": [
        1550.5216878255208,
        1553.5721842447917,
        1553.26904296875,
        1552.7983805338542
      ],
      "preprocess_ms_per_rank": [
        49.60523506005605,
        0.3620866934458415,
        29.056468685468037,
        56.912907679875694
      ],
      "dispatch_ms_per_rank": [
        760.7798890272776,
        761.8198849360148,
        761.3360994656881,
        761.0574905872345
      ],
      "combine_ms_per_rank": [
        708.4371276696523,
        758.0486620267233,
        732.6557784080505,
        710.7966034412384
      ],
      "dispatch_bytes_per_rank": [
        356952192,
        345412224,
        329938176,
        315513216
      ],
      "combine_bytes_per_rank": [
        356777984,
        345243648,
        329777152,
        315359232
      ],
      "tokens_out_per_rank": [
        10888,
        10536,
        10064,
        9624
      ],
      "assignments_per_rank": [
        87104,
        84288,
        80512,
        76992
      ]
    },
    "layer_46": {
      "total_ms_avg": 1295.8396708170574,
      "total_ms_max": 1296.9427897135417,
      "dispatch_ms_avg": 633.3207760751247,
      "dispatch_ms_max": 634.1399236917496,
      "combine_ms_avg": 523.7211581369241,
      "combine_ms_max": 631.5119860172272,
      "preprocess_ms_avg": 110.49327399333319,
      "preprocess_ms_max": 306.11846999327344,
      "total_ms_per_rank": [
        1296.9427897135417,
        1294.3868815104167,
        1296.3143717447917,
        1295.7146402994792
      ],
      "preprocess_ms_per_rank": [
        0.3587503433227539,
        83.92314898967743,
        306.11846999327344,
        51.57272664705912
      ],
      "dispatch_ms_per_rank": [
        634.059698621432,
        634.1399236917496,
        632.2444502909979,
        632.8390316963196
      ],
      "combine_ms_per_rank": [
        631.5119860172272,
        546.5404160022736,
        335.75577557086945,
        581.0764549573263
      ],
      "dispatch_bytes_per_rank": [
        356952192,
        345412224,
        329938176,
        315513216
      ],
      "combine_bytes_per_rank": [
        356777984,
        345243648,
        329777152,
        315359232
      ],
      "tokens_out_per_rank": [
        10888,
        10536,
        10064,
        9624
      ],
      "assignments_per_rank": [
        87104,
        84288,
        80512,
        76992
      ]
    },
    "layer_47": {
      "total_ms_avg": 1269.3538106282551,
      "total_ms_max": 1270.7205403645833,
      "dispatch_ms_avg": 619.2139264345169,
      "dispatch_ms_max": 620.2964393297831,
      "combine_ms_avg": 509.9692192574342,
      "combine_ms_max": 617.6381849447886,
      "preprocess_ms_avg": 113.32234078645706,
      "preprocess_ms_max": 209.35671031475067,
      "total_ms_per_rank": [
        1268.0574137369792,
        1268.5919596354167,
        1270.0453287760417,
        1270.7205403645833
      ],
      "preprocess_ms_per_rank": [
        0.3408866723378499,
        187.57044124603271,
        56.02132491270701,
        209.35671031475067
      ],
      "dispatch_ms_per_rank": [
        620.2964393297831,
        619.7218050559362,
        618.5523916482925,
        618.2850697040558
      ],
      "combine_ms_per_rank": [
        617.6381849447886,
        433.82269136110943,
        565.24931204319,
        423.1666886806488
      ],
      "dispatch_bytes_per_rank": [
        356952192,
        345412224,
        329938176,
        315513216
      ],
      "combine_bytes_per_rank": [
        356777984,
        345243648,
        329777152,
        315359232
      ],
      "tokens_out_per_rank": [
        10888,
        10536,
        10064,
        9624
      ],
      "assignments_per_rank": [
        87104,
        84288,
        80512,
        76992
      ]
    },
    "layer_5": {
      "total_ms_avg": 1225.9663492838542,
      "total_ms_max": 1227.59716796875,
      "dispatch_ms_avg": 598.4345325827599,
      "dispatch_ms_max": 599.4444683790207,
      "combine_ms_avg": 480.3586158454418,
      "combine_ms_max": 595.7019463380178,
      "preprocess_ms_avg": 117.55975264310835,
      "preprocess_ms_max": 215.75206764539084,
      "total_ms_per_rank": [
        1227.59716796875,
        1226.5373128255208,
        1222.8318277994792,
        1226.8990885416667
      ],
      "preprocess_ms_per_rank": [
        0.33036331335703534,
        200.59132532278696,
        215.75206764539084,
        53.56525429089864
      ],
      "dispatch_ms_per_rank": [
        599.4444683790207,
        598.7564146518707,
        597.559274593989,
        597.977972706159
      ],
      "combine_ms_per_rank": [
        595.7019463380178,
        393.6999967098236,
        387.4271386861801,
        544.6053816477457
      ],
      "dispatch_bytes_per_rank": [
        356952192,
        345412224,
        329938176,
        315513216
      ],
      "combine_bytes_per_rank": [
        356777984,
        345243648,
        329777152,
        315359232
      ],
      "tokens_out_per_rank": [
        10888,
        10536,
        10064,
        9624
      ],
      "assignments_per_rank": [
        87104,
        84288,
        80512,
        76992
      ]
    },
    "layer_6": {
      "total_ms_avg": 1150.639119466146,
      "total_ms_max": 1153.0902099609375,
      "dispatch_ms_avg": 559.5730124215285,
      "dispatch_ms_max": 560.4148976405462,
      "combine_ms_avg": 523.5528860588868,
      "combine_ms_max": 560.9592536687851,
      "preprocess_ms_avg": 39.53870790203412,
      "preprocess_ms_max": 94.96422930558522,
      "total_ms_per_rank": [
        1150.3216959635417,
        1147.755859375,
        1153.0902099609375,
        1151.3887125651042
      ],
      "preprocess_ms_per_rank": [
        53.22338064511617,
        0.3603803316752116,
        9.606841325759888,
        94.96422930558522
      ],
      "dispatch_ms_per_rank": [
        558.764191309611,
        560.4148976405462,
        559.3816666603088,
        559.731294075648
      ],
      "combine_ms_per_rank": [
        508.94229531288147,
        557.1334076325098,
        560.9592536687851,
        467.17658762137097
      ],
      "dispatch_bytes_per_rank": [
        356952192,
        345412224,
        329938176,
        315513216
      ],
      "combine_bytes_per_rank": [
        356777984,
        345243648,
        329777152,
        315359232
      ],
      "tokens_out_per_rank": [
        10888,
        10536,
        10064,
        9624
      ],
      "assignments_per_rank": [
        87104,
        84288,
        80512,
        76992
      ]
    },
    "layer_7": {
      "total_ms_avg": 1234.0196838378906,
      "total_ms_max": 1235.5584309895833,
      "dispatch_ms_avg": 603.7934327423571,
      "dispatch_ms_max": 604.9984899759293,
      "combine_ms_avg": 527.2917865713437,
      "combine_ms_max": 595.9179603258768,
      "preprocess_ms_avg": 72.29415799180667,
      "preprocess_ms_max": 131.64654397964478,
      "total_ms_per_rank": [
        1234.5938313802083,
        1235.5584309895833,
        1233.115478515625,
        1232.8109944661458
      ],
      "preprocess_ms_per_rank": [
        0.3309030532836914,
        53.568917632102966,
        103.63026730219524,
        131.64654397964478
      ],
      "dispatch_ms_per_rank": [
        604.9984899759293,
        603.6629636685053,
        603.3915679852167,
        603.1207093397776
      ],
      "combine_ms_per_rank": [
        595.9179603258768,
        550.3733916680018,
        495.30768462022144,
        467.56810967127484
      ],
      "dispatch_bytes_per_rank": [
        356952192,
        345412224,
        329938176,
        315513216
      ],
      "combine_bytes_per_rank": [
        356777984,
        345243648,
        329777152,
        315359232
      ],
      "tokens_out_per_rank": [
        10888,
        10536,
        10064,
        9624
      ],
      "assignments_per_rank": [
        87104,
        84288,
        80512,
        76992
      ]
    },
    "layer_8": {
      "total_ms_avg": 1146.3359985351562,
      "total_ms_max": 1149.166259765625,
      "dispatch_ms_avg": 560.8136016925176,
      "dispatch_ms_max": 561.5689417123795,
      "combine_ms_avg": 491.00660011172295,
      "combine_ms_max": 556.7922539313635,
      "preprocess_ms_avg": 67.49159440398216,
      "preprocess_ms_max": 149.09685369332632,
      "total_ms_per_rank": [
        1149.166259765625,
        1144.9620361328125,
        1148.1487223307292,
        1143.0669759114583
      ],
      "preprocess_ms_per_rank": [
        0.31852996349334717,
        67.77436562379201,
        52.77662833531698,
        149.09685369332632
      ],
      "dispatch_ms_per_rank": [
        561.5328703324,
        561.5689417123795,
        560.128715356191,
        560.0238793691
      ],
      "combine_ms_per_rank": [
        556.7922539313635,
        488.31568789482117,
        507.3591816027959,
        411.55927701791126
      ],
      "dispatch_bytes_per_rank": [
        356952192,
        345412224,
        329938176,
        315513216
      ],
      "combine_bytes_per_rank": [
        356777984,
        345243648,
        329777152,
        315359232
      ],
      "tokens_out_per_rank": [
        10888,
        10536,
        10064,
        9624
      ],
      "assignments_per_rank": [
        87104,
        84288,
        80512,
        76992
      ]
    },
    "layer_9": {
      "total_ms_avg": 1062.809875488281,
      "total_ms_max": 1065.2689208984375,
      "dispatch_ms_avg": 519.5859132309754,
      "dispatch_ms_max": 520.5133146842321,
      "combine_ms_avg": 455.11604159077007,
      "combine_ms_max": 509.27094129721326,
      "preprocess_ms_avg": 59.53566669424375,
      "preprocess_ms_max": 112.83126870791118,
      "total_ms_per_rank": [
        1062.0307210286458,
        1065.2689208984375,
        1062.4085286458333,
        1061.5313313802083
      ],
      "preprocess_ms_per_rank": [
        0.3593769868214925,
        112.83126870791118,
        54.25023372968038,
        70.70178735256195
      ],
      "dispatch_ms_per_rank": [
        520.5133146842321,
        520.0883626143137,
        518.8688376347224,
        518.8731379906336
      ],
      "combine_ms_per_rank": [
        509.27094129721326,
        400.9894680182139,
        466.5392012993495,
        443.6645557483037
      ],
      "dispatch_bytes_per_rank": [
        356952192,
        345412224,
        329938176,
        315513216
      ],
      "combine_bytes_per_rank": [
        356777984,
        345243648,
        329777152,
        315359232
      ],
      "tokens_out_per_rank": [
        10888,
        10536,
        10064,
        9624
      ],
      "assignments_per_rank": [
        87104,
        84288,
        80512,
        76992
      ]
    }
  }
}